direct7/__init__.py
direct7/client.py
direct7/errors.py
direct7/number_lookup.py
direct7/slack.py
direct7/sms.py
direct7/verify.py
direct7/viber.py
direct7/whatsapp.py
direct7-0.0.15.dist-info/METADATA
direct7-0.0.15.dist-info/WHEEL
direct7-0.0.15.dist-info/licenses/LICENSE
direct7-0.0.15.dist-info/RECORD
