Metadata-Version: 2.4
Name: direct7
Version: 0.0.15
Summary: Python SDK for Direct7  Platform REST API
Project-URL: Homepage, https://github.com/d7networks/direct7-python-sdk
Project-URL: Bug Tracker, https://github.com/d7networks/direct7-python-sdk/issues
Author-email: Direct7 Networks <support@d7networks.com>
License-File: LICENSE
Classifier: License :: OSI Approved :: MIT License
Classifier: Operating System :: OS Independent
Classifier: Programming Language :: Python :: 3
Requires-Python: >=3.6
